CA_model.py
Iceing_model.py
evaluation.py
topography.py
web_interface.py
ComplexSystemSimulation-1.0.0.dist-info/METADATA
ComplexSystemSimulation-1.0.0.dist-info/WHEEL
ComplexSystemSimulation-1.0.0.dist-info/top_level.txt
ComplexSystemSimulation-1.0.0.dist-info/RECORD
