Metadata-Version: 2.1
Name: ComplexSystemSimulation
Version: 1.0.0
Summary: Artic ice melt ponds Cellular Automata (CA) model
Home-page: 
License: UNKNOWN
Platform: UNKNOWN
Requires-Dist: numpy (~=1.21.6)
Requires-Dist: numba (~=0.56.4)
Requires-Dist: scipy (~=1.7.3)
Requires-Dist: matplotlib (~=3.5.3)
Requires-Dist: streamlit (~=1.23.1)
Requires-Dist: plotly (~=5.14.1)
Requires-Dist: imageio (~=2.31.1)
